{"trip":{"id":2729842,"userId":711078,"url":"israel-2729842","title":"Israël","places":"Israel","pictureColor":6195124,"start":1683955653001,"end":1684611525264,"deleted":false,"create":1683955572301,"profileVisibility":1,"showComments":true,"sync":1686898968400,"entryCount":28,"followerCount":28,"pictureCount":230,"categoryId":1,"pictureGuid":"TNwtNbOnk1HlEvhF","isPublic":true,"visibility":1,"authors":[{"userId":711078,"firstName":"Manon","lastName":"Goossen","pictureGuid":"defaultJw7wNqgUG","trips":10,"status":0,"url":"6pyqzqbn"}],"status":3,"followers":[{"userId":4508811,"firstName":"gretta","lastName":"strookappe","pictureGuid":"defaultmYUByfGRj","trips":0,"status":0,"url":"vdkjxsbv"},{"userId":4604781,"firstName":"Janneke","lastName":"Streppel","pictureGuid":"defaultA45ZrH-s1","trips":0,"status":0,"url":"ffenkslb"},{"userId":1526593,"firstName":"Leo","lastName":"Kluin","pictureGuid":"defaultkZuJW1fFY","trips":1,"status":0,"url":"hzhdeqmi"},{"userId":4492631,"firstName":"Marleen","lastName":"Hiddink","pictureGuid":"defaultE0IEbXiBw","trips":0,"status":0,"url":"z1lw5dmd"}]},"entries":[{"id":91655329,"tripId":2729842,"categoryId":10,"visibility":1,"comment":"Inmiddels zijn we geland en veilig weer terug aan het Sint Maartenserf in Twello. We hebben een super fijne en bijzondere vakantie gehad samen \uD83E\uDDE1","lat":32.0852999,"lng":34.78176759999999,"deleted":false,"create":1684611525264,"timezone":"Europe/Amsterdam","sync":1684751613846,"authorId":711078,"top1LikeId":9,"top2LikeId":4,"likeCount":3,"userLikeId":0,"commentCount":3,"topReacted":[{"userId":1508001,"firstName":"Petra","lastName":"Goossen","pictureGuid":"defaultqHucxbfz9","trips":0,"status":0,"url":"ooprupbk"},{"userId":1508755,"firstName":"Tanja","lastName":"Linthorst","pictureGuid":"LOnK2R4ERcoEmC0J","trips":0,"status":0,"url":"rs4oudt0"},{"userId":1092479,"firstName":"marja","lastName":"streppel","pictureGuid":"defaultBSubJUizD","trips":0,"status":0,"url":"ka6yqlkt"}],"pictures":[{"createDate":1684612448812,"guid":"TOh9WgVv7evQiydA","height":4032,"width":3024},{"createDate":1684612457795,"guid":"TOh951OH08VHC7hl","height":4032,"width":3024},{"createDate":1684649794866,"guid":"TOh9SJ6S7NBh9bDP","height":4032,"width":3024},{"createDate":1684649858792,"guid":"TOhfb3Y34wCvIyoM","height":4032,"width":3024}],"editors":[{"userId":711078,"firstName":"Manon","lastName":"Goossen","pictureGuid":"defaultJw7wNqgUG","trips":10,"status":0,"url":"6pyqzqbn"}],"fitness":null},{"id":91655207,"tripId":2729842,"categoryId":10,"visibility":1,"comment":"Vandaag was helaas onze laatste ochtend in Israël. Na een koffie aan het strand (bij het buffet wordt geen koffie geserveerd wegens sabbat) en een laatste wandeling langs de boulevard is het tijd om terug te keren naar het vliegveld. Opa blijft gigantische gefascineerd door het drukke verkeer en geniet weer van de rit. Op het vliegveld kregen we weer speciale assistentie, maar desondanks was het nog wel even chaotisch. Opa mocht niet verder bij de metaalpoortjes (we waren even z'n nieuwe knie vergeten te noemen) en bij de gate werden we plotseling van elkaar gescheiden waarbij opa en ik samen in het speciale busje zaten zonder paspoorten (tot frustratie van de fanatieke medewerkster). We hebben laat geluncht in het vliegtuig omdat het ons door de medewerkers sterk werd afgeraden om op het vliegveld bij de McDonald's te eten: het blijkt een Koshere vestiging en alle gefrituurde gerechten (dus alles) worden dan op vrijdagmiddag vast bereid voor zaterdag.","lat":32.0852999,"lng":34.78176759999999,"deleted":false,"create":1684571254035,"timezone":"Europe/Amsterdam","sync":1684751504076,"authorId":711078,"top1LikeId":4,"top2LikeId":0,"likeCount":2,"userLikeId":0,"commentCount":0,"topReacted":[{"userId":1508001,"firstName":"Petra","lastName":"Goossen","pictureGuid":"defaultqHucxbfz9","trips":0,"status":0,"url":"ooprupbk"},{"userId":1092479,"firstName":"marja","lastName":"streppel","pictureGuid":"defaultBSubJUizD","trips":0,"status":0,"url":"ka6yqlkt"}],"pictures":[{"createDate":1684656967000,"guid":"TOgYZ3alZcyIV7bf","height":1024,"width":768},{"createDate":1684656967000,"guid":"TOgYJtKA43bnjy8W","height":1024,"width":768},{"createDate":1684656967000,"guid":"TOgYXDSCPUjsATiL","height":1024,"width":768},{"createDate":1684656967000,"guid":"TOgYAWJKtKyzyZKr","height":768,"width":1024},{"createDate":1684656967000,"guid":"TOgYD9YCmpSv0v4S","height":1024,"width":768},{"createDate":1684656967000,"guid":"TOgYBt9WAXWsPu3w","height":1024,"width":768},{"createDate":1684656967000,"guid":"TOgYiM723WYGX8Ig","height":1024,"width":768},{"createDate":1684656967000,"guid":"TOgY5xhDau8IPj7S","height":768,"width":1024},{"createDate":1684656967000,"guid":"TOgYUPYIpSJDyHBf","height":1024,"width":768},{"createDate":1684656967000,"guid":"TOgYtIWJp2lxUOgp","height":1024,"width":768}],"editors":[{"userId":711078,"firstName":"Manon","lastName":"Goossen","pictureGuid":"defaultJw7wNqgUG","trips":10,"status":0,"url":"6pyqzqbn"}],"fitness":null},{"id":91655198,"tripId":2729842,"categoryId":10,"visibility":1,"comment":"\uD83D\uDCCD Tel Aviv","lat":32.0852999,"lng":34.78176759999999,"deleted":false,"create":1684516567000,"timezone":"Europe/Amsterdam","sync":1684751511231,"authorId":711078,"top1LikeId":4,"top2LikeId":9,"likeCount":2,"userLikeId":0,"commentCount":0,"topReacted":[{"userId":1508001,"firstName":"Petra","lastName":"Goossen","pictureGuid":"defaultqHucxbfz9","trips":0,"status":0,"url":"ooprupbk"},{"userId":1092479,"firstName":"marja","lastName":"streppel","pictureGuid":"defaultBSubJUizD","trips":0,"status":0,"url":"ka6yqlkt"}],"pictures":[{"createDate":1684657598278,"guid":"TOgW7IPPHQztx9Fo","height":1024,"width":768},{"createDate":1684657598848,"guid":"TOgWETWEm4CYNIO1","height":1024,"width":768},{"createDate":1684657599419,"guid":"TOgW11zDFAXtxjfc","height":1024,"width":768},{"createDate":1684657600053,"guid":"TOgWLHn8cH7bdZVK","height":1024,"width":768},{"createDate":1684657600618,"guid":"TOgWbLOpxbBOjbIv","height":1024,"width":768},{"createDate":1684657601280,"guid":"TOgWxHL8JAagAkeV","height":1024,"width":768},{"createDate":1684657601853,"guid":"TOgWXZhKpqOV5JAT","height":768,"width":1024},{"createDate":1684657602413,"guid":"TOgWNG1CjHCxI9XF","height":768,"width":1024},{"createDate":1684657603098,"guid":"TOgWeZ0Sad9JvzJU","height":1024,"width":768},{"createDate":1684657603689,"guid":"TOgWmSetee7KB7W9","height":1024,"width":768}],"editors":[{"userId":711078,"firstName":"Manon","lastName":"Goossen","pictureGuid":"defaultJw7wNqgUG","trips":10,"status":0,"url":"6pyqzqbn"}],"fitness":null},{"id":91630533,"tripId":2729842,"categoryId":9,"visibility":1,"comment":"We zwaaien het meer van Galilea gedag en rijden via het Karmelgebergte en Haifa naar Tel Aviv. Met 26° en zon hebben we de perfecte temperatuur om de rolstoel de boulevard op en neer te duwen. 's Middags zijn we naar Jaffa gewandeld, een oude havenstad die inmiddels onderdeel is van Tel Aviv. Super mooie wijk met een leuke markt en veel gezelligheid op straat en op de terassen. Voor opa wederom genoeg te zien hier! \n\nHet is inmiddels weer vrijdagavond dus de Sabbat is opnieuw begonnen. Nog een positief gevolg van het omgooien van de originele route: in Tel Aviv is met sabbat een stuk meer open dan in Jeruzalem, dus we kunnen onze geweldige vakantie afsluiten bij een gezellig restaurantje in de buurt van de Carmelmarkt. We krijgen o.a. Challah (zoet brood dat wordt gegeten met de Sabbat) en Lars en ik proberen Synia (een Palestijns ovengerecht met lamsgehakt). Opa sluit uiteraard af met een cognacje en ik probeer voor de gelegenheid Arak Ashkelon (een soort israelische ouzo).","lat":32.0686723,"lng":34.7692451,"deleted":false,"create":1684503189556,"timezone":"Asia/Jerusalem","sync":1684662020841,"authorId":711078,"top1LikeId":4,"top2LikeId":0,"likeCount":3,"userLikeId":0,"commentCount":2,"topReacted":[{"userId":1092479,"firstName":"marja","lastName":"streppel","pictureGuid":"defaultBSubJUizD","trips":0,"status":0,"url":"ka6yqlkt"},{"userId":1508001,"firstName":"Petra","lastName":"Goossen","pictureGuid":"defaultqHucxbfz9","trips":0,"status":0,"url":"ooprupbk"},{"userId":1508755,"firstName":"Tanja","lastName":"Linthorst","pictureGuid":"LOnK2R4ERcoEmC0J","trips":0,"status":0,"url":"rs4oudt0"}],"pictures":[{"createDate":1684656967000,"guid":"TOgVNI5jHoEpDxFP","height":1024,"width":768},{"createDate":1684656967000,"guid":"TOgV7VBu0jerpdrv","height":1024,"width":768},{"createDate":1684656967000,"guid":"TOgVsgZwksBiEp4x","height":1024,"width":768},{"createDate":1684656967000,"guid":"TOgVziv66bCaz6a1","height":1024,"width":768},{"createDate":1684656967000,"guid":"TOgVB4IpCCRyGguP","height":768,"width":1024},{"createDate":1684656967000,"guid":"TOgVQ78k0jaxGYP4","height":1024,"width":768},{"createDate":1684656967000,"guid":"TOgVDihjW8UfB1bd","height":1024,"width":768},{"createDate":1684656967000,"guid":"TOgVFRDlZ6mFa3wI","height":768,"width":1024},{"createDate":1684656967000,"guid":"TOgVeuxKXaTubRtY","height":1024,"width":768},{"createDate":1684656967000,"guid":"TOgVs1veyrEWiweC","height":768,"width":1024}],"editors":[{"userId":711078,"firstName":"Manon","lastName":"Goossen","pictureGuid":"defaultJw7wNqgUG","trips":10,"status":0,"url":"6pyqzqbn"}],"fitness":null},{"id":91621967,"tripId":2729842,"categoryId":10,"visibility":1,"comment":"Als laatste grote wens voor de vakantie zou opa graag naar een kerkdienst gaan. Zodoende zaten wij om 19:30 in de St. Peter's kerk voor de hemelvaartsmis. Nadien sluiten we Tiberias af met eten en drankjes bij hetzelfde restaurantje aan de boulevard, daar was immers de cognac zo lekker en het personeel zo vriendelijk. Vanaf het terras hebben we interessant uitzicht op de Koshere kebabzaken waar het de hele avond stampvol is met orthodoxe joden. Ook kijkt opa z'n ogen uit bij de grote hoeveelheden damesgezelschappen die waarschijnlijk op een soort kerkreis zijn.","lat":32.72051232,"lng":35.1821784,"deleted":false,"create":1684441827580,"timezone":"Asia/Jerusalem","sync":1684565803648,"authorId":711078,"top1LikeId":4,"top2LikeId":1,"likeCount":4,"userLikeId":0,"commentCount":1,"topReacted":[{"userId":1092479,"firstName":"marja","lastName":"streppel","pictureGuid":"defaultBSubJUizD","trips":0,"status":0,"url":"ka6yqlkt"},{"userId":1550159,"firstName":"Lily","lastName":"Goossen-Turubassa","pictureGuid":"default4F469Uemb","trips":0,"status":0,"url":"ldpfiusc"},{"userId":4003152,"firstName":"Bennie","lastName":"Doeve","pictureGuid":"defaultfFuUnNqw0","trips":0,"status":0,"url":"3sbhkqpg"}],"pictures":[{"createDate":1684481468784,"guid":"TNvBfvPAXwwE2YYm","height":3024,"width":4032},{"createDate":1684481469945,"guid":"TNvBUMj8SUha7HL0","height":4032,"width":3024},{"createDate":1684481470871,"guid":"TNvB7qU8YQavhSIP","height":1024,"width":768},{"createDate":1684481471958,"guid":"TNvBBBB7P2HXIHz5","height":1024,"width":768},{"createDate":1684481472793,"guid":"TNvBHQBTKVAtbes3","height":768,"width":1024},{"createDate":1684481474421,"guid":"TNvBmmlvaHfYpEtg","height":4032,"width":3024},{"createDate":1684481475527,"guid":"TNvBmieDpKs8bsTU","height":4032,"width":3024},{"createDate":1684481476731,"guid":"TNvBpuIQBeGC1Hrd","height":3024,"width":4032},{"createDate":1684481477642,"guid":"TNvBeIlZsfuJ2SmW","height":1024,"width":768},{"createDate":1684348783717,"guid":"TNvLdqVtKEwMaGvA","height":4032,"width":3024}],"editors":[{"userId":711078,"firstName":"Manon","lastName":"Goossen","pictureGuid":"defaultJw7wNqgUG","trips":10,"status":0,"url":"6pyqzqbn"}],"fitness":null},{"id":91612831,"tripId":2729842,"categoryId":9,"visibility":1,"comment":"Ondertussen zijn we overigens ontzettend blij dat we de originele reisroute hebben omgedraaid en we vandaag niet in Jeruzalem zijn. Het is momenteel Jerusalem Day en de stad is overspoeld met fanatieke nationalistische Israëliërs die hun verovering van de stad komen vieren en er zijn 3500 agenten ingezet om de boel onder controle te houden. Geen geschikte omstandigheden voor een stedentripje met je 86-jarige opa.","lat":32.78690368,"lng":35.54334152,"deleted":false,"create":1684424988661,"timezone":"Asia/Jerusalem","sync":1684506710059,"authorId":711078,"top1LikeId":3,"top2LikeId":4,"likeCount":2,"userLikeId":0,"commentCount":0,"topReacted":[{"userId":1508001,"firstName":"Petra","lastName":"Goossen","pictureGuid":"defaultqHucxbfz9","trips":0,"status":0,"url":"ooprupbk"},{"userId":1092479,"firstName":"marja","lastName":"streppel","pictureGuid":"defaultBSubJUizD","trips":0,"status":0,"url":"ka6yqlkt"}],"pictures":[{"createDate":1684425609350,"guid":"TNgA9umq2osTyAEl","height":1844,"width":1080},{"createDate":1684426521475,"guid":"TNgQUqiZnnRwsWrZ","height":1869,"width":1077}],"editors":[{"userId":711078,"firstName":"Manon","lastName":"Goossen","pictureGuid":"defaultJw7wNqgUG","trips":10,"status":0,"url":"6pyqzqbn"}],"fitness":null},{"id":91621950,"tripId":2729842,"categoryId":10,"visibility":1,"comment":"\uD83D\uDCCD Nazareth","lat":32.7350101,"lng":35.2129579,"deleted":false,"create":1684404346000,"timezone":"Asia/Jerusalem","sync":1684511374558,"authorId":711078,"top1LikeId":9,"top2LikeId":4,"likeCount":3,"userLikeId":0,"commentCount":0,"topReacted":[{"userId":1508001,"firstName":"Petra","lastName":"Goossen","pictureGuid":"defaultqHucxbfz9","trips":0,"status":0,"url":"ooprupbk"},{"userId":1092479,"firstName":"marja","lastName":"streppel","pictureGuid":"defaultBSubJUizD","trips":0,"status":0,"url":"ka6yqlkt"},{"userId":1550159,"firstName":"Lily","lastName":"Goossen-Turubassa","pictureGuid":"default4F469Uemb","trips":0,"status":0,"url":"ldpfiusc"}],"pictures":[{"createDate":1684418746000,"guid":"TNvzG8jPQVJ74w7L","height":1024,"width":768},{"createDate":1684481415876,"guid":"TNvzhYR4NJNOqa1q","height":1024,"width":768},{"createDate":1684481417553,"guid":"TNvzRGri1Z6RzyQd","height":1024,"width":768},{"createDate":1684481419079,"guid":"TNvzQOon3XVyZohH","height":1024,"width":768},{"createDate":1684481420676,"guid":"TNvz6zyWZW3Pxp80","height":1024,"width":768},{"createDate":1684481422867,"guid":"TNvzHB9g9Fu3ghJh","height":1024,"width":768},{"createDate":1684481424575,"guid":"TNvzeI1HdP20FvDG","height":1024,"width":768},{"createDate":1684481426519,"guid":"TNvzQgbdVgCBIG5P","height":1024,"width":768},{"createDate":1684481428420,"guid":"TNvz54jpA8Ava5to","height":1024,"width":768},{"createDate":1684481430558,"guid":"TNvz1FmRaXZUOn4f","height":1024,"width":768}],"editors":[{"userId":711078,"firstName":"Manon","lastName":"Goossen","pictureGuid":"defaultJw7wNqgUG","trips":10,"status":0,"url":"6pyqzqbn"}],"fitness":null},{"id":91612309,"tripId":2729842,"categoryId":10,"visibility":1,"comment":"Vandaag zijn we met de auto naar Nazareth gereden. Een belangrijke bezienswaardigheid is de Kerk van de Aankondiging, maar we beginnen ondertussen wel een klein beetje kerk-moe te raken. Het centrum van Nazareth is daarentegen ontzettend gezellig, met leuke straatjes en gezellige Arabische koffietentjes. We hebben een leuk winkeltje bezocht waar ze ingelijste tekstjes Arabische poëzie verkochten en hebben uitgebreid geluncht bij een leuk restaurantje (voor opa het gastronomische hoogtepunt van de week: ze hadden soep!). Opa kletst uiteraard met jan en alleman op de markt en in het restaurant en vindt alles interessant. Waar we ons in Jeruzalem en Tiberias hebben verbaasd over de grote hoeveelheden ultra orthodoxe joden is deze stad voor het grootste deel Arabisch wat voor een mooie afwisseling zorgt.","lat":32.699635,"lng":35.303546,"deleted":false,"create":1684397089578,"timezone":"Asia/Jerusalem","sync":1684506738276,"authorId":711078,"top1LikeId":4,"top2LikeId":8,"likeCount":2,"userLikeId":0,"commentCount":0,"topReacted":[{"userId":1508001,"firstName":"Petra","lastName":"Goossen","pictureGuid":"defaultqHucxbfz9","trips":0,"status":0,"url":"ooprupbk"},{"userId":1092479,"firstName":"marja","lastName":"streppel","pictureGuid":"defaultBSubJUizD","trips":0,"status":0,"url":"ka6yqlkt"}],"pictures":[{"createDate":1684481082000,"guid":"TNvygUkNYiO6qaak","height":1024,"width":768},{"createDate":1684480817000,"guid":"TNvyQFWHxIX4LA3W","height":1024,"width":768},{"createDate":1684480817000,"guid":"TNvyi2xK5Ypl811J","height":768,"width":1024},{"createDate":1684480817000,"guid":"TNvyyOGIVknRJdlp","height":1024,"width":737},{"createDate":1684481095000,"guid":"TNvy8Pc487I7UhNX","height":1024,"width":768},{"createDate":1684480817000,"guid":"TNvy2Ed3KJDQvFWF","height":768,"width":1024},{"createDate":1684411821076,"guid":"TNvymRPiFCgcr8J7","height":4032,"width":3024},{"createDate":1684401081890,"guid":"TNvyf6yWvUMVbMpr","height":4032,"width":3024},{"createDate":1684418746000,"guid":"TNvyUuH0hf70RRn7","height":1024,"width":768},{"createDate":1684413757074,"guid":"TNvyzHJujCJzPd9X","height":3024,"width":4032}],"editors":[{"userId":711078,"firstName":"Manon","lastName":"Goossen","pictureGuid":"defaultJw7wNqgUG","trips":10,"status":0,"url":"6pyqzqbn"}],"fitness":null},{"id":91596000,"tripId":2729842,"categoryId":3,"visibility":1,"comment":"Vanochtend zijn we na het ontbijt richting het noorden vertrokken. Een bezoek aan een Kibboetz (een soort landbouwgemeenschap) stond nog hoog op de wensenlijst van opa. Daarna hebben we ook nog de Oase van Ein Gedi bezocht, waar we een kort rolstoelvriendelijk wandelpad tot een waterval hebben gelopen. Het is 41° en er is nauwelijks schaduw te bekennen, dus we vinden het niet erg om niet de volledige trail te kunnen lopen. \n\nVanaf Ein Gedi rijden we in zo'n 2,5 uur naar Tiberias. Onderweg komen we langs een hoop Palestijnse dorpjes en opa heeft overal wel een verhaal bij. We lunchen en drinken een biertje met uitzicht op het meer van Tiberias, we hebben het goed voor elkaar hier!","lat":31.47143520741059,"lng":35.386027470231056,"deleted":false,"create":1684321816000,"timezone":"Asia/Jerusalem","sync":1684447296809,"authorId":711078,"top1LikeId":2,"top2LikeId":4,"likeCount":5,"userLikeId":2,"commentCount":1,"topReacted":[{"userId":4003152,"firstName":"Bennie","lastName":"Doeve","pictureGuid":"defaultfFuUnNqw0","trips":0,"status":0,"url":"3sbhkqpg"},{"userId":703611,"firstName":"Marvin","lastName":"Linthorst","pictureGuid":"defaultJu3IAOAcC","trips":0,"status":0,"url":"clwh7mub"},{"userId":1092479,"firstName":"marja","lastName":"streppel","pictureGuid":"defaultBSubJUizD","trips":0,"status":0,"url":"ka6yqlkt"}],"pictures":[{"createDate":1684322024415,"guid":"TMOJXcfaBB54t0jQ","height":1024,"width":768},{"createDate":1684322025611,"guid":"TMOJTve4SLfc0n4h","height":1024,"width":768},{"createDate":1684322026614,"guid":"TMOJVhMHYoQtcsjD","height":1024,"width":768},{"createDate":1684322027751,"guid":"TMOJ2BuN2twACbRI","height":768,"width":1024},{"createDate":1684322028803,"guid":"TMOJjSKiCdMmsZgr","height":1024,"width":768},{"createDate":1684322029811,"guid":"TMOJ7iMkRV0Hb2mU","height":1024,"width":768},{"createDate":1684322031250,"guid":"TMOJSFZdNc1PKaw0","height":3024,"width":4032},{"createDate":1684322032335,"guid":"TMOJ3FdKVNECcX7x","height":1024,"width":768},{"createDate":1684322033529,"guid":"TMOJ5Cpnn7ZmzNer","height":768,"width":1024},{"createDate":1684322034684,"guid":"TMOJu6xbbZtMuhYY","height":1024,"width":768}],"editors":[{"userId":711078,"firstName":"Manon","lastName":"Goossen","pictureGuid":"defaultJw7wNqgUG","trips":10,"status":0,"url":"6pyqzqbn"}],"fitness":null},{"id":91587773,"tripId":2729842,"categoryId":15,"visibility":1,"comment":"De rest van de middag hebben we aan het zwembad gelegen en lekker gegeten en gedronken bij het restaurantje ernaast. Het is 40° met een briesje die aanvoelt als een heteluchtoven dus heel veel meer zit er niet in. Toen de zon onder begon te gaan zijn we uiteindelijk nog even naar de zee gegaan om een tijdje in het zoute water te drijven. Opa overzag de boel vanaf de waterkant.","lat":31.2000512,"lng":35.3612481,"deleted":false,"create":1684252649310,"timezone":"Asia/Jerusalem","sync":1684447378550,"authorId":711078,"top1LikeId":4,"top2LikeId":3,"likeCount":6,"userLikeId":3,"commentCount":0,"topReacted":[{"userId":2974378,"firstName":"Jan","lastName":"Turubassa","pictureGuid":"defaultVAL-8b3Jn","trips":0,"status":0,"url":"powy358l"},{"userId":703611,"firstName":"Marvin","lastName":"Linthorst","pictureGuid":"defaultJu3IAOAcC","trips":0,"status":0,"url":"clwh7mub"},{"userId":1092479,"firstName":"marja","lastName":"streppel","pictureGuid":"defaultBSubJUizD","trips":0,"status":0,"url":"ka6yqlkt"}],"pictures":[{"createDate":1684252296000,"guid":"TMwp9w1pCZq8psti","height":768,"width":1024},{"createDate":1684247940767,"guid":"TMwpm0XEHJtXwinA","height":3024,"width":4032},{"createDate":1684253676000,"guid":"TMwpGQPDCe0F4jTm","height":768,"width":1024},{"createDate":1684253676000,"guid":"TMwpYak7NOPr9CvS","height":1024,"width":768},{"createDate":1684252296000,"guid":"TMwpLGmjhTMJaG3y","height":768,"width":1024},{"createDate":1684247870013,"guid":"TMwpUks01c1oungL","height":4032,"width":3024},{"createDate":1684244697017,"guid":"TMwpfmlgO9qspmAx","height":4032,"width":3024},{"createDate":1684239204635,"guid":"TMwpYL477Ln46boN","height":4032,"width":3024},{"createDate":1684253676000,"guid":"TMwpR1xeFDd7fNDG","height":1024,"width":768},{"createDate":1684321767961,"guid":"TMOFVUSfFSKvZFeV","height":1024,"width":768}],"editors":[{"userId":711078,"firstName":"Manon","lastName":"Goossen","pictureGuid":"defaultJw7wNqgUG","trips":10,"status":0,"url":"6pyqzqbn"}],"fitness":null},{"id":91587542,"tripId":2729842,"categoryId":10,"visibility":1,"comment":"Vanochtend zijn we optijd vertrokken richting het fort (of de ruïnes) van Masada. We komen tegelijk aan met een paar bussen schoolkinderen (opa vindt de drukte geweldig), maar hebben wederom veel voordeel van de rolstoel en mogen met voorrang de lift in. Volgens opa hadden Lars en ik ook prima het voetpad (het slangenpad) kunnen nemen, maar gezien de temperaturen vinden we het geen probleem dat die gesloten is. Met het liftje bereiken we de top van de berg. Vanaf hier kunnen we over het terrein langs de verschillende delen van de ruïne wandelen en hebben we een schitterend uitzicht over de omgeving.","lat":31.2000207,"lng":35.3612059,"deleted":false,"create":1684226611764,"timezone":"Asia/Jerusalem","sync":1684447455846,"authorId":711078,"top1LikeId":4,"top2LikeId":7,"likeCount":6,"userLikeId":4,"commentCount":0,"topReacted":[{"userId":1508001,"firstName":"Petra","lastName":"Goossen","pictureGuid":"defaultqHucxbfz9","trips":0,"status":0,"url":"ooprupbk"},{"userId":1550159,"firstName":"Lily","lastName":"Goossen-Turubassa","pictureGuid":"default4F469Uemb","trips":0,"status":0,"url":"ldpfiusc"},{"userId":1092479,"firstName":"marja","lastName":"streppel","pictureGuid":"defaultBSubJUizD","trips":0,"status":0,"url":"ka6yqlkt"}],"pictures":[{"createDate":1684252281000,"guid":"TMwgrni56WATAXQT","height":768,"width":1024},{"createDate":1684226077257,"guid":"TMwgtPb28UBvIf5i","height":3024,"width":4032},{"createDate":1684224757845,"guid":"TMwgCTxF1LdM9kP6","height":1800,"width":4000},{"createDate":1684252281000,"guid":"TMwg1PszyJLgVlNF","height":1024,"width":768},{"createDate":1684224356457,"guid":"TMwgbzUfXX7WSvnd","height":4032,"width":3024},{"createDate":1684227474585,"guid":"TMwgw3RxACo4hZK2","height":4032,"width":3024},{"createDate":1684225982230,"guid":"TMwgOvqRwwKfJGdR","height":3024,"width":4032},{"createDate":1684252281000,"guid":"TMwgDy8rAln2Zb5w","height":1024,"width":768},{"createDate":1684227902355,"guid":"TMwgJ4MNLb8rEv4V","height":4032,"width":3024},{"createDate":1684252281000,"guid":"TMwgpxxRn5NzjrOC","height":768,"width":1024}],"editors":[{"userId":711078,"firstName":"Manon","lastName":"Goossen","pictureGuid":"defaultJw7wNqgUG","trips":10,"status":0,"url":"6pyqzqbn"}],"fitness":null},{"id":91582337,"tripId":2729842,"categoryId":10,"visibility":1,"comment":"Als we aankomen in Ein Bokek is het inmiddels 36°. Lars en ik zijn wel een tikkeltje oververhit en moe (opa uiteraard niet) dus we lassen even een rustmoment in bij het zwembad. 's Avonds lopen we richting de Dode Zee om een eindje langs het strand te wandelen. Er zijn afgezien van wat snackbars nauwelijks strandtentjes te vinden om wat te eten (wellicht tast de eierlucht van de zee de eetlust aan) dus uiteindelijk schuiven we aan bij het gezellige tentje naast ons zwembad. Het was weer een geslaagde dag!","lat":31.2000868,"lng":35.3612713,"deleted":false,"create":1684176280866,"timezone":"Asia/Jerusalem","sync":1684264173230,"authorId":711078,"top1LikeId":4,"top2LikeId":2,"likeCount":5,"userLikeId":4,"commentCount":0,"topReacted":[{"userId":1092479,"firstName":"marja","lastName":"streppel","pictureGuid":"defaultBSubJUizD","trips":0,"status":0,"url":"ka6yqlkt"},{"userId":1550159,"firstName":"Lily","lastName":"Goossen-Turubassa","pictureGuid":"default4F469Uemb","trips":0,"status":0,"url":"ldpfiusc"},{"userId":703611,"firstName":"Marvin","lastName":"Linthorst","pictureGuid":"defaultJu3IAOAcC","trips":0,"status":0,"url":"clwh7mub"}],"pictures":[{"createDate":1684237805000,"guid":"TMs67B0aai8EULTR","height":1024,"width":768},{"createDate":1684237805000,"guid":"TMs66NL0OtpaBVh4","height":1024,"width":768},{"createDate":1684237805000,"guid":"TMs6gyBQ4X0jXWv0","height":768,"width":1024},{"createDate":1684237805000,"guid":"TMs68du0TGX3KulJ","height":1024,"width":768},{"createDate":1684237805000,"guid":"TMs6J8f3QNt1Ntfq","height":1024,"width":768},{"createDate":1684237869662,"guid":"TMs6QwDWS2Ux5n9e","height":1800,"width":4000},{"createDate":1684237875389,"guid":"TMs6Snx9NRIkbPy6","height":4032,"width":3024}],"editors":[{"userId":711078,"firstName":"Manon","lastName":"Goossen","pictureGuid":"defaultJw7wNqgUG","trips":10,"status":0,"url":"6pyqzqbn"}],"fitness":null},{"id":91579553,"tripId":2729842,"categoryId":10,"visibility":1,"comment":"'s Middags zijn we naar Ein Bokek aan de Dode Zee gereden. De route was schitterend, het leek wel of we door een film reden. We durfden niet echt uit te stappen omdat de weg door Palestijns grondgebied loopt (maar beheerd wordt door Israël). \n\nOnderweg nog geluncht in de buurt van de oase van Ein Gedi, met o.a. shakshuka, labneh en hummus. Opa dacht dat we nu misschien wel op de mooiste plek op aarde waren.","lat":31.200073,"lng":35.3612594,"deleted":false,"create":1684155209000,"timezone":"Asia/Jerusalem","sync":1684240534414,"authorId":711078,"top1LikeId":2,"top2LikeId":4,"likeCount":3,"userLikeId":0,"commentCount":0,"topReacted":[{"userId":1508755,"firstName":"Tanja","lastName":"Linthorst","pictureGuid":"LOnK2R4ERcoEmC0J","trips":0,"status":0,"url":"rs4oudt0"},{"userId":1508001,"firstName":"Petra","lastName":"Goossen","pictureGuid":"defaultqHucxbfz9","trips":0,"status":0,"url":"ooprupbk"},{"userId":1092479,"firstName":"marja","lastName":"streppel","pictureGuid":"defaultBSubJUizD","trips":0,"status":0,"url":"ka6yqlkt"}],"pictures":[{"createDate":1684180409000,"guid":"TMcJ4Q8KQxCwwbc5","height":768,"width":1024},{"createDate":1684180634303,"guid":"TMcJXnTrogaiuu4N","height":3024,"width":4032},{"createDate":1684180637018,"guid":"TMcJVyI4uW015lcj","height":768,"width":1024},{"createDate":1684180644443,"guid":"TMcJ9O8QNpXiX9Wd","height":2048,"width":1536},{"createDate":1684180649516,"guid":"TMcJWWNjt99V4Arx","height":1536,"width":2048},{"createDate":1684180652127,"guid":"TMcJluXVNEqKu6Lj","height":1024,"width":768},{"createDate":1684180665132,"guid":"TMcJuQkyLi6WzAZR","height":2048,"width":1536},{"createDate":1684180675888,"guid":"TMcJDMQzmiveFwGT","height":4032,"width":3024},{"createDate":1684180697352,"guid":"TMcJhGG0B5ffJHSv","height":3024,"width":4032},{"createDate":1684180707444,"guid":"TMcJ53viKBlQzH5P","height":1816,"width":4032}],"editors":[{"userId":711078,"firstName":"Manon","lastName":"Goossen","pictureGuid":"defaultJw7wNqgUG","trips":10,"status":0,"url":"6pyqzqbn"}],"fitness":null},{"id":91576339,"tripId":2729842,"categoryId":10,"visibility":1,"comment":"Vanochtend zijn we uitgecheckt en zijn we met de auto naar Yad Vashem gereden, het nationale holocaustmuseum. Echt heel bijzonder en indrukwekkend.","lat":31.19930213,"lng":35.36147125,"deleted":false,"create":1684140245954,"timezone":"Asia/Jerusalem","sync":1684257583130,"authorId":711078,"top1LikeId":7,"top2LikeId":9,"likeCount":5,"userLikeId":9,"commentCount":1,"topReacted":[{"userId":1092479,"firstName":"marja","lastName":"streppel","pictureGuid":"defaultBSubJUizD","trips":0,"status":0,"url":"ka6yqlkt"},{"userId":1550159,"firstName":"Lily","lastName":"Goossen-Turubassa","pictureGuid":"default4F469Uemb","trips":0,"status":0,"url":"ldpfiusc"},{"userId":703611,"firstName":"Marvin","lastName":"Linthorst","pictureGuid":"defaultJu3IAOAcC","trips":0,"status":0,"url":"clwh7mub"}],"pictures":[{"createDate":1684169081000,"guid":"TMcnUDv060Kr9cvl","height":768,"width":1024},{"createDate":1684142024974,"guid":"TMcn3hGHjUt3zClp","height":3024,"width":4032},{"createDate":1684169081000,"guid":"TMcnUmp3jiHeZ2XH","height":1024,"width":768},{"createDate":1684169081000,"guid":"TMcnXAvmxnra938p","height":1024,"width":768},{"createDate":1684169081000,"guid":"TMcneUiiwQOnNWwh","height":768,"width":1024},{"createDate":1684141060638,"guid":"TMcngQxCechjxQJz","height":3024,"width":4032},{"createDate":1684169081000,"guid":"TMcnK5RaCEoWULKb","height":768,"width":1024},{"createDate":1684169081000,"guid":"TMcn67U9La5y1nYy","height":1024,"width":768},{"createDate":1684169081000,"guid":"TMcnarjKeLEtHXdL","height":768,"width":1024},{"createDate":1684169081000,"guid":"TMcno8FZNJYuvfG4","height":768,"width":1024}],"editors":[{"userId":711078,"firstName":"Manon","lastName":"Goossen","pictureGuid":"defaultJw7wNqgUG","trips":10,"status":0,"url":"6pyqzqbn"}],"fitness":null},{"id":91576288,"tripId":2729842,"categoryId":10,"visibility":1,"comment":"We hebben gister zo ongeveer 2 dagen in 1 dag beleefd, dus hierbij nog wat resterende fotootjes van Jeruzalem!","lat":31.19930345,"lng":35.36146422,"deleted":false,"create":1684129043967,"timezone":"Asia/Jerusalem","sync":1684257540091,"authorId":711078,"top1LikeId":3,"top2LikeId":4,"likeCount":3,"userLikeId":3,"commentCount":0,"topReacted":[{"userId":1508001,"firstName":"Petra","lastName":"Goossen","pictureGuid":"defaultqHucxbfz9","trips":0,"status":0,"url":"ooprupbk"},{"userId":1092479,"firstName":"marja","lastName":"streppel","pictureGuid":"defaultBSubJUizD","trips":0,"status":0,"url":"ka6yqlkt"},{"userId":703611,"firstName":"Marvin","lastName":"Linthorst","pictureGuid":"defaultJu3IAOAcC","trips":0,"status":0,"url":"clwh7mub"}],"pictures":[{"createDate":1684123468000,"guid":"TM8DYelEgRFjbySp","height":1024,"width":768},{"createDate":1684123442000,"guid":"TM8D6XMFt9z7HZpl","height":1024,"width":768},{"createDate":1684123442000,"guid":"TM8DQxnvuiZNTwwf","height":1024,"width":768},{"createDate":1684123442000,"guid":"TM8DPc3xIEGGyKQV","height":1024,"width":768},{"createDate":1684123442000,"guid":"TM8Ds206CezSU0tI","height":1024,"width":768},{"createDate":1684123442000,"guid":"TM8DFx2nZWnYs651","height":1024,"width":768},{"createDate":1684063160387,"guid":"TM8DGEYhhEGXDLkV","height":3024,"width":4032},{"createDate":1684123442000,"guid":"TM8DPSE7f9FWAJCE","height":768,"width":1024},{"createDate":1684123442000,"guid":"TM8DKUvkqWeAFtNR","height":1024,"width":768},{"createDate":1684123442000,"guid":"TM8DXwccfSUVma9M","height":1024,"width":768}],"editors":[{"userId":711078,"firstName":"Manon","lastName":"Goossen","pictureGuid":"defaultJw7wNqgUG","trips":10,"status":0,"url":"6pyqzqbn"}],"fitness":null},{"id":91576180,"tripId":2729842,"categoryId":8,"visibility":1,"comment":"\uD83D\uDCCD Israelische muur Bethlehem","lat":31.70538209999999,"lng":35.2024425,"deleted":false,"create":1684077800957,"timezone":"Asia/Jerusalem","sync":1684240391426,"authorId":711078,"top1LikeId":2,"top2LikeId":4,"likeCount":3,"userLikeId":0,"commentCount":0,"topReacted":[{"userId":1508001,"firstName":"Petra","lastName":"Goossen","pictureGuid":"defaultqHucxbfz9","trips":0,"status":0,"url":"ooprupbk"},{"userId":1550159,"firstName":"Lily","lastName":"Goossen-Turubassa","pictureGuid":"default4F469Uemb","trips":0,"status":0,"url":"ldpfiusc"},{"userId":1092479,"firstName":"marja","lastName":"streppel","pictureGuid":"defaultBSubJUizD","trips":0,"status":0,"url":"ka6yqlkt"}],"pictures":[{"createDate":1684123227000,"guid":"TM8pP2FltMQP8Tyx","height":1024,"width":768},{"createDate":1684075043999,"guid":"TM8pJqzH1oMvQdrs","height":3024,"width":4032},{"createDate":1684123227000,"guid":"TM8pKxD3ijoZoOve","height":768,"width":1024},{"createDate":1684123227000,"guid":"TM8pLyIn4apbefVN","height":1024,"width":768},{"createDate":1684123227000,"guid":"TM8pkISsm5UZPgDH","height":1024,"width":768},{"createDate":1684123227000,"guid":"TM8pDtc1xqiYBOKR","height":1024,"width":768},{"createDate":1684123227000,"guid":"TM8pbDQ1LIsH2xNB","height":768,"width":1024},{"createDate":1684123227000,"guid":"TM8pYLXCLNqSnWs4","height":1024,"width":768},{"createDate":1684123227000,"guid":"TM8pePFzpkYE6Qrh","height":1024,"width":768},{"createDate":1684123227000,"guid":"TM8p0EkeHioEy1op","height":768,"width":1024}],"editors":[{"userId":711078,"firstName":"Manon","lastName":"Goossen","pictureGuid":"defaultJw7wNqgUG","trips":10,"status":0,"url":"6pyqzqbn"}],"fitness":null},{"id":91576081,"tripId":2729842,"categoryId":10,"visibility":1,"comment":"Opa had nog de grote wens om Bethlehem te bezoeken. Het blijkt echter niet mogelijk (/niet verstandig) om met onze eigen auto (met israelisch kenteken) naar Bethlehem te rijden, het ligt namelijk op de Westelijke Jordaanoever. Zodoende hebben we eind van de middag via het hotel nog een chauffeur geregeld die ons erheen wou brengen. \n\nDe bestemming was o.a. de geboortekerk van Jezus, maar we vonden de reis opzich vele malen indrukwekkender. We moesten zowel de heen- als de terugweg door een flink bewaakte checkpoint en we zagen her en der ommuurde israelische settlements midden tussen de Palestijnse gebieden. Ook zagen we een paar wegen die over de volledige lengte waren omheind met 2 rijen hekken en prikkeldraad. \n\nVoordat we naar de kerk gingen hebben we eerst nog de muur bezocht. De Westoevermuur is een 10m hoge betonnen muur (en hekken, prikkeldraad en torens) van ruim 700km die langs de volledige westelijke Jordaanoever loopt. Werkelijk bizar om te zien.","lat":31.70538209999999,"lng":35.2024425,"deleted":false,"create":1684073138954,"timezone":"Asia/Jerusalem","sync":1684240360313,"authorId":711078,"top1LikeId":4,"top2LikeId":7,"likeCount":3,"userLikeId":0,"commentCount":0,"topReacted":[{"userId":1508001,"firstName":"Petra","lastName":"Goossen","pictureGuid":"defaultqHucxbfz9","trips":0,"status":0,"url":"ooprupbk"},{"userId":1550159,"firstName":"Lily","lastName":"Goossen-Turubassa","pictureGuid":"default4F469Uemb","trips":0,"status":0,"url":"ldpfiusc"},{"userId":1092479,"firstName":"marja","lastName":"streppel","pictureGuid":"defaultBSubJUizD","trips":0,"status":0,"url":"ka6yqlkt"}],"pictures":[{"createDate":1684076261496,"guid":"TM8id2bbz8Bgld86","height":1816,"width":4032},{"createDate":1684078711388,"guid":"TM8iXCFUCIi6Fa8r","height":4032,"width":3024},{"createDate":1684078135924,"guid":"TM8iMjwNy0GearUP","height":3024,"width":4032},{"createDate":1684077073487,"guid":"TM8ie3ZdNQaIRi4r","height":4032,"width":3024},{"createDate":1684077019619,"guid":"TM8iJthKERRWLH6C","height":4032,"width":3024},{"createDate":1684076905163,"guid":"TM8iSfDCSxdBk56U","height":4032,"width":3024},{"createDate":1684076898919,"guid":"TM8iUKcwXcehmR7k","height":3024,"width":4032},{"createDate":1684123485000,"guid":"TM8il3mExSxs0qoP","height":1024,"width":768},{"createDate":1684153327000,"guid":"TM8iDYtiI3ODaZcE","height":2048,"width":1536},{"createDate":1684166443655,"guid":"TM8UjGR1jiUTnCZL","height":768,"width":1024}],"editors":[{"userId":711078,"firstName":"Manon","lastName":"Goossen","pictureGuid":"defaultJw7wNqgUG","trips":10,"status":0,"url":"6pyqzqbn"}],"fitness":null},{"id":91575732,"tripId":2729842,"categoryId":14,"visibility":1,"comment":"Vanaf de Klaagmuur zijn we, met speciale assistentie van de militairen vanwege de rolstoel, naar de tempelberg gegaan. Deze plek is zowel voor de Joden als de Moslims heilig. Volgens de Moslims zou Mohammed op de plek van de Rotskoepel naar de hemel zijn gegaan, volgens de Joden zou op deze berg de 1e Joodse tempel hebben gestaan en zou dit de plek zijn waar Abraham zijn zoon zou offeren. De Joden beschouwen deze plek als zodanig heilig dat het voor hen niet is toegestaan om de tempelberg te betreden.","lat":31.778478569038835,"lng":35.23564103990793,"deleted":false,"create":1684065774984,"timezone":"Asia/Jerusalem","sync":1684240284798,"authorId":711078,"top1LikeId":2,"top2LikeId":3,"likeCount":3,"userLikeId":0,"commentCount":0,"topReacted":[{"userId":1508001,"firstName":"Petra","lastName":"Goossen","pictureGuid":"defaultqHucxbfz9","trips":0,"status":0,"url":"ooprupbk"},{"userId":1550159,"firstName":"Lily","lastName":"Goossen-Turubassa","pictureGuid":"default4F469Uemb","trips":0,"status":0,"url":"ldpfiusc"},{"userId":1092479,"firstName":"marja","lastName":"streppel","pictureGuid":"defaultBSubJUizD","trips":0,"status":0,"url":"ka6yqlkt"}],"pictures":[{"createDate":1684123330000,"guid":"TM7X77DNsX1TNJik","height":1024,"width":768},{"createDate":1684052819445,"guid":"TM7XC7BDt9TzvNFE","height":3024,"width":4032},{"createDate":1684123330000,"guid":"TM7XAyNrHzq42KXL","height":1024,"width":768},{"createDate":1684163036157,"guid":"TM7XLIQ2RWnKMeBk","height":1024,"width":768},{"createDate":1684123330000,"guid":"TM7XcBTPNSLkqoYB","height":1024,"width":768},{"createDate":1684123330000,"guid":"TM7XAaBvMDkNsaoa","height":768,"width":1024},{"createDate":1684123330000,"guid":"TM7XUPHq8gP1mYYk","height":1024,"width":768},{"createDate":1684123330000,"guid":"TM7XrIDOnIcAR6NJ","height":1024,"width":768},{"createDate":1684123330000,"guid":"TM7XmPIrWBXrRUWD","height":1024,"width":768},{"createDate":1684052047038,"guid":"TM7XzHIBUrJ81l6r","height":3024,"width":4032}],"editors":[{"userId":711078,"firstName":"Manon","lastName":"Goossen","pictureGuid":"defaultJw7wNqgUG","trips":10,"status":0,"url":"6pyqzqbn"}],"fitness":null},{"id":91571015,"tripId":2729842,"categoryId":14,"visibility":1,"comment":"\uD83D\uDCCD de Rotskoepel","lat":31.7804677,"lng":35.2182167,"deleted":false,"create":1684061879717,"timezone":"Asia/Jerusalem","sync":1684240277460,"authorId":711078,"top1LikeId":4,"top2LikeId":0,"likeCount":1,"userLikeId":0,"commentCount":0,"topReacted":[{"userId":1092479,"firstName":"marja","lastName":"streppel","pictureGuid":"defaultBSubJUizD","trips":0,"status":0,"url":"ka6yqlkt"}],"pictures":[{"createDate":1684123330000,"guid":"TLZe1PKxBUlMW6Mw","height":818,"width":1023}],"editors":[{"userId":711078,"firstName":"Manon","lastName":"Goossen","pictureGuid":"defaultJw7wNqgUG","trips":10,"status":0,"url":"6pyqzqbn"}],"fitness":null},{"id":91571007,"tripId":2729842,"categoryId":9,"visibility":1,"comment":"Uiteraard hebben we ook een bezoek gebracht aan de Western Wall, oftewel de Klaagmuur. De ingang tot het plein is zwaar beveiligd met militairen en we moeten eerst door metaaldetectoren voordat we naar de muur mochten. Hier scheiden onze wegen want er is een apart deel voor mannen en vrouwen. Opa en Lars krijgen een keppeltje op en mogen daarna de muur bekijken. Helaas zijn we onze pen en papier vergeten. Opa heeft nogsteeds de tijd van z'n leven en fungeert continu als reisleider.","lat":31.7804562,"lng":35.2182122,"deleted":false,"create":1684054588679,"timezone":"Asia/Jerusalem","sync":1684232239264,"authorId":711078,"top1LikeId":4,"top2LikeId":7,"likeCount":3,"userLikeId":0,"commentCount":0,"topReacted":[{"userId":1508001,"firstName":"Petra","lastName":"Goossen","pictureGuid":"defaultqHucxbfz9","trips":0,"status":0,"url":"ooprupbk"},{"userId":1092479,"firstName":"marja","lastName":"streppel","pictureGuid":"defaultBSubJUizD","trips":0,"status":0,"url":"ka6yqlkt"},{"userId":1550159,"firstName":"Lily","lastName":"Goossen-Turubassa","pictureGuid":"default4F469Uemb","trips":0,"status":0,"url":"ldpfiusc"}],"pictures":[{"createDate":1684123403000,"guid":"TM7JZwrWUHowCy7R","height":1024,"width":768},{"createDate":1684123460000,"guid":"TM7JABtGDN3LRjqb","height":768,"width":1024},{"createDate":1684050975186,"guid":"TM7JYHYn2ikEzgl4","height":3024,"width":4032},{"createDate":1684123403000,"guid":"TM7JwphULuXC1bnQ","height":1024,"width":768},{"createDate":1684051260651,"guid":"TM7JQUxfRkRv1FqD","height":4032,"width":3024},{"createDate":1684051554113,"guid":"TM7JbgiZqxDjgMwi","height":4032,"width":3024},{"createDate":1684052215747,"guid":"TM7Jl2pMeJnZnqi1","height":1800,"width":4000},{"createDate":1684051360147,"guid":"TM7Jg6xx7h4kRQE6","height":1816,"width":4032},{"createDate":1684051273114,"guid":"TM7J543luIDf0auH","height":4032,"width":3024},{"createDate":1684051891746,"guid":"TM7Jbz3uyPGIc7hZ","height":3024,"width":4032}],"editors":[{"userId":711078,"firstName":"Manon","lastName":"Goossen","pictureGuid":"defaultJw7wNqgUG","trips":10,"status":0,"url":"6pyqzqbn"}],"fitness":null},{"id":91570526,"tripId":2729842,"categoryId":8,"visibility":1,"comment":"De Via Dolorosa loopt verder door de oude binnenstad  waarbij er nog enkele belangrijke punten gemarkeerd zijn (o.a. waar hij het kruis liet vallen, waar hij Maria zag etc.). Het eindigt bij de Heilige Grafkerk (of Kerk van de Wederopstanding), waar Jezus zou zijn gekruisigd, begraven en opgestaan. Het was wederom een uitdagende route, maar meer dan de moeite waard toen we er eenmaal waren. Opa kijkt met enorme bewondering om zich heen en kan de hoeveelheid aan alles bijna niet bevatten.","lat":31.7804784,"lng":35.2182626,"deleted":false,"create":1684049194876,"timezone":"Asia/Jerusalem","sync":1684232209374,"authorId":711078,"top1LikeId":7,"top2LikeId":4,"likeCount":3,"userLikeId":0,"commentCount":0,"topReacted":[{"userId":1508001,"firstName":"Petra","lastName":"Goossen","pictureGuid":"defaultqHucxbfz9","trips":0,"status":0,"url":"ooprupbk"},{"userId":1092479,"firstName":"marja","lastName":"streppel","pictureGuid":"defaultBSubJUizD","trips":0,"status":0,"url":"ka6yqlkt"},{"userId":1550159,"firstName":"Lily","lastName":"Goossen-Turubassa","pictureGuid":"default4F469Uemb","trips":0,"status":0,"url":"ldpfiusc"}],"pictures":[{"createDate":1684123284000,"guid":"TLXSpJNmDHgUxT2v","height":1024,"width":768},{"createDate":1684123284000,"guid":"TLXSbLSkTpJnxbb0","height":768,"width":1024},{"createDate":1684123284000,"guid":"TLXS8IV96YYtpLYm","height":1024,"width":768},{"createDate":1684060094193,"guid":"TLXSyqSTY2VE4fh7","height":4000,"width":1800},{"createDate":1684123284000,"guid":"TLXS3JXQBx4xBz1d","height":1024,"width":768},{"createDate":1684123284000,"guid":"TLXSnBxXeDnEtain","height":1024,"width":768},{"createDate":1684060451555,"guid":"TLXS735MJNHoPYCh","height":4032,"width":3024},{"createDate":1684123284000,"guid":"TLXScVLxJNUD4ZfD","height":1024,"width":768},{"createDate":1684060358897,"guid":"TLXSAFCAH8oYXqSl","height":3024,"width":4032},{"createDate":1684123284000,"guid":"TLXSu6p4qUQt02y4","height":1024,"width":768}],"editors":[{"userId":711078,"firstName":"Manon","lastName":"Goossen","pictureGuid":"defaultJw7wNqgUG","trips":10,"status":0,"url":"6pyqzqbn"}],"fitness":null},{"id":91570517,"tripId":2729842,"categoryId":8,"visibility":1,"comment":"Vanaf de Lionsgate begint de 'Via Dolorosa': de lijdensweg die Jezus heeft afgelegd, ook wel de kruisweg (Via Crucis) genoemd. De 1e stop is de Kerk van de Veroordeling, waar Jezus door Pontius Pilates ter dood zou zijn veroordeeld (2-5). Vervolgens zijn we naar de gevangenis gegaan waar Jezus samen met o.a. Barabas werd vastgehouden (6-10). Opa kijkt z'n ogen uit. Ondanks dat hij hier als eens eerder is geweest is hij enorm onder de indruk van alles.","lat":31.7804803,"lng":35.2182675,"deleted":false,"create":1684044640899,"timezone":"Asia/Jerusalem","sync":1684232181536,"authorId":711078,"top1LikeId":9,"top2LikeId":4,"likeCount":3,"userLikeId":0,"commentCount":1,"topReacted":[{"userId":1092479,"firstName":"marja","lastName":"streppel","pictureGuid":"defaultBSubJUizD","trips":0,"status":0,"url":"ka6yqlkt"},{"userId":1508001,"firstName":"Petra","lastName":"Goossen","pictureGuid":"defaultqHucxbfz9","trips":0,"status":0,"url":"ooprupbk"},{"userId":1550159,"firstName":"Lily","lastName":"Goossen-Turubassa","pictureGuid":"default4F469Uemb","trips":0,"status":0,"url":"ldpfiusc"}],"pictures":[{"createDate":1684124592865,"guid":"TLXFsOG2AkvMiwIZ","height":1024,"width":768},{"createDate":1684124596476,"guid":"TLXFBGCbyajS3dQO","height":1024,"width":768},{"createDate":1684124600770,"guid":"TLXF0cYk4uJzKW68","height":1024,"width":768},{"createDate":1684124604141,"guid":"TLXFiPHoHGtwUvwH","height":1024,"width":768},{"createDate":1684124605992,"guid":"TLXFdI6cGYRX93BW","height":1024,"width":768},{"createDate":1684124612191,"guid":"TLXFxx0gr35HSoND","height":1632,"width":1224},{"createDate":1684124615180,"guid":"TLXFL0NyGlMTabBq","height":1024,"width":768},{"createDate":1684124619901,"guid":"TLXFD3wB4GgBFSO6","height":1024,"width":768},{"createDate":1684124627196,"guid":"TLXF2MtkUeSVojpo","height":1632,"width":1224},{"createDate":1684124629655,"guid":"TLXFSpLv6CChWLO0","height":1024,"width":768}],"editors":[{"userId":711078,"firstName":"Manon","lastName":"Goossen","pictureGuid":"defaultJw7wNqgUG","trips":10,"status":0,"url":"6pyqzqbn"}],"fitness":null},{"id":91553743,"tripId":2729842,"categoryId":14,"visibility":1,"comment":"Opa had bedacht dat we tussen 07:30 en 08:00 zouden opstaan, het moest immers wel een beetje vakantie blijven. Om 07:15 stond hij echter gedoucht, aangekleed en wel voor de deur: hij had helemaal geen horloge of wekker dus hij kwam informeren hoe laat het was. We hebben lekker in het hotel ontbeten. Lars en ik hebben salade gemaakt met gegrilde groente en feta, opa wou liever geen 'koeienvoer' en ging voor de boterhammen met kaas en ei. Maarliefst 4 stuks, want we hebben een druk programma vandaag!\n\nGezien de hoeveelheid trappen en steile straatjes hebben we besloten ons met een taxi bij de Lions gate af te laten zetten, een van de poorten naar het oude centrum.","lat":31.7804863,"lng":35.2181973,"deleted":false,"create":1684041982242,"timezone":"Asia/Jerusalem","sync":1684162398847,"authorId":711078,"top1LikeId":1,"top2LikeId":4,"likeCount":4,"userLikeId":0,"commentCount":1,"topReacted":[{"userId":1092479,"firstName":"marja","lastName":"streppel","pictureGuid":"defaultBSubJUizD","trips":0,"status":0,"url":"ka6yqlkt"},{"userId":2974378,"firstName":"Jan","lastName":"Turubassa","pictureGuid":"defaultVAL-8b3Jn","trips":0,"status":0,"url":"powy358l"},{"userId":1508001,"firstName":"Petra","lastName":"Goossen","pictureGuid":"defaultqHucxbfz9","trips":0,"status":0,"url":"ooprupbk"}],"pictures":[{"createDate":1684042073383,"guid":"TLBvRNYuvpyTDQpi","height":4032,"width":3024},{"createDate":1684047583129,"guid":"TLXpxaLatbUBm0RN","height":4032,"width":3024},{"createDate":1684047599293,"guid":"TLXpPbDQtZcZmKjh","height":4032,"width":3024},{"createDate":1684123442000,"guid":"TLXpFyATcywN4HTC","height":1024,"width":768},{"createDate":1684123442000,"guid":"TLXsRaxQMl2L3e6p","height":1024,"width":768},{"createDate":1684047629254,"guid":"TLXsecFJENnh7AZh","height":4032,"width":3024},{"createDate":1684123403000,"guid":"TLXFNNrkISFJVqOd","height":1024,"width":768}],"editors":[{"userId":711078,"firstName":"Manon","lastName":"Goossen","pictureGuid":"defaultJw7wNqgUG","trips":10,"status":0,"url":"6pyqzqbn"}],"fitness":null},{"id":91550163,"tripId":2729842,"categoryId":10,"visibility":1,"comment":"Last minute bedacht Lars, geïnspireerd door de prachtige invloed van golden hour, dat we de zonsondergang wel vanaf de olijfberg konden bekijken. Volgens internet zou het er niet mogelijk zijn om auto's te parkeren dus besloten we per taxi te gaan. Toen we over de smalle weg naar boven reden hadden we hier overigens ook geen spijt van. Helaas was de zon al grotendeels onder toen we aankwamen, maar het uitzicht over de stad was alsnog waanzinnig! Vanaf de Olijfberg hadden we verder prachtig uitzicht over de gouden rotskoepel op de tempelberg en keek je neer op de indrukwekkende Joodse begraafplaats. Daarnaast hebben we tijdens de taxiritjes een volledige stadstour gekregen, waarbij de chauffeur ons vanalles vertelde over de verschillende stadspoorten (o.a. waar Jezus de stad binnen ging op een ezel met Palmpasen) en ons o.a. de kerk van Maria Magdalena en de Hemelvaattkerk aanwees. Op deze manier konden we toch een groot deel van de stad zien. Het was een geslaagde dag!","lat":31.7804942,"lng":35.2182801,"deleted":false,"create":1684000908000,"timezone":"Asia/Jerusalem","sync":1684149718909,"authorId":711078,"top1LikeId":4,"top2LikeId":9,"likeCount":7,"userLikeId":0,"commentCount":1,"topReacted":[{"userId":4003152,"firstName":"Bennie","lastName":"Doeve","pictureGuid":"defaultfFuUnNqw0","trips":0,"status":0,"url":"3sbhkqpg"},{"userId":1550159,"firstName":"Lily","lastName":"Goossen-Turubassa","pictureGuid":"default4F469Uemb","trips":0,"status":0,"url":"ldpfiusc"},{"userId":1092479,"firstName":"marja","lastName":"streppel","pictureGuid":"defaultBSubJUizD","trips":0,"status":0,"url":"ka6yqlkt"}],"pictures":[{"createDate":1684042031815,"guid":"TLrtNXIQk4TZ2GTa","height":768,"width":1024},{"createDate":1684042042279,"guid":"TLrtN7sgkk8AOPFQ","height":1024,"width":768},{"createDate":1684042053117,"guid":"TLrt0ExkFNfjUW4z","height":768,"width":1024},{"createDate":1684042062158,"guid":"TLrtG6pBuZyeawTH","height":1024,"width":768},{"createDate":1684042070384,"guid":"TLrtDiYUi4GDji8w","height":768,"width":1024},{"createDate":1684042084720,"guid":"TLrt0jKSclC3BUrx","height":1024,"width":768}],"editors":[{"userId":711078,"firstName":"Manon","lastName":"Goossen","pictureGuid":"defaultJw7wNqgUG","trips":10,"status":0,"url":"6pyqzqbn"}],"fitness":null},{"id":91549834,"tripId":2729842,"categoryId":14,"visibility":1,"comment":"Met nieuwe energie zijn we 's avonds richting het oude centrum gewandeld. Eén ding is zeker: wij hoeven deze week niet meer te sporten!\n\nHet oude centrum is volledig omringd door enorme stadsmuren, echt heel erg mooi om te zien. We zijn via de Jaffa Poort naar binnen gelopen en hebben door wat straatjes gewandeld. Nog best een uitdaging met de rolstoel over de stenen. We komen ontzettend veel traditioneel geklede Joden tegen die van en naar het oude centrum lopen, wellicht om te bidden bij de klaagmuur. Zo ver zijn wij echter niet gekomen: er is vrij veel hoogteverschil dus we besluiten dat deel van de stad voor morgen te bewaren. Gelukkig hebben we in dit stukje stad al genoeg om onze ogen uit te kijken!","lat":31.7804787,"lng":35.2182891,"deleted":false,"create":1683995877979,"timezone":"Asia/Jerusalem","sync":1684164976753,"authorId":711078,"top1LikeId":4,"top2LikeId":2,"likeCount":5,"userLikeId":0,"commentCount":0,"topReacted":[{"userId":4003152,"firstName":"Bennie","lastName":"Doeve","pictureGuid":"defaultfFuUnNqw0","trips":0,"status":0,"url":"3sbhkqpg"},{"userId":1550159,"firstName":"Lily","lastName":"Goossen-Turubassa","pictureGuid":"default4F469Uemb","trips":0,"status":0,"url":"ldpfiusc"},{"userId":1092479,"firstName":"marja","lastName":"streppel","pictureGuid":"defaultBSubJUizD","trips":0,"status":0,"url":"ka6yqlkt"}],"pictures":[{"createDate":1684004549000,"guid":"TLrtz0Ef4rC2yyMp","height":1024,"width":768},{"createDate":1683992945939,"guid":"TLrt4dw9MWaEwwBS","height":3024,"width":4032},{"createDate":1684004558000,"guid":"TLrtQjw44aAp286B","height":1024,"width":768},{"createDate":1684004539000,"guid":"TLrtFJu3ivL3RlvA","height":1024,"width":768},{"createDate":1683992442180,"guid":"TLrtPilI533jFjoy","height":4032,"width":3024},{"createDate":1684004543000,"guid":"TLrtaNCAQYQslkGW","height":1024,"width":768},{"createDate":1683991128524,"guid":"TLrt20035Driv2Hm","height":4032,"width":3024},{"createDate":1683991190266,"guid":"TLrtgHPxsEesVcUR","height":3024,"width":4032},{"createDate":1684004515000,"guid":"TLrtikyJAbo98ldz","height":1024,"width":768},{"createDate":1684003214885,"guid":"TLrtDx1scvuAmpc4","height":1890,"width":1080}],"editors":[{"userId":711078,"firstName":"Manon","lastName":"Goossen","pictureGuid":"defaultJw7wNqgUG","trips":10,"status":0,"url":"6pyqzqbn"}],"fitness":null},{"id":91549771,"tripId":2729842,"categoryId":10,"visibility":1,"comment":"Gezien de onrust de laatste dagen hebben we flink getwijfeld of we Jeruzalem en Tel Aviv evt zouden moeten overslaan (en of Israël überhaupt nog wel een verstandige optie was). Uiteindelijk toch gekozen om maar gewoon te gaan en het per dag te bekijken.\n\nNa een hoop regelwerk op het vliegveld (simkaarten scoren, dollars wisselen voor Israelische Sjekels, huurauto fixen) rijden we uiteindelijk tegen 15:00 eindelijk (doodop, zie foto 3) richting Jeruzalem. Het is opvallend uitgestorven op de wegen, waarbij we ons uiteindelijk bedenken dat het natuurlijk nog Shabbat is. Veel dingen zijn hierdoor nog gesloten, maar gelukkig vinden we toch een restaurantje in het zonnetje. Opa is vastbesloten het er vollop van te nemen deze vakantie en neemt 2 luxe glaasjes cognac als aperitief en zalm voor het hoofdgerecht.","lat":31.7804992,"lng":35.2182641,"deleted":false,"create":1683984004160,"timezone":"Asia/Jerusalem","sync":1684187472551,"authorId":711078,"top1LikeId":4,"top2LikeId":0,"likeCount":4,"userLikeId":0,"commentCount":1,"topReacted":[{"userId":1508755,"firstName":"Tanja","lastName":"Linthorst","pictureGuid":"LOnK2R4ERcoEmC0J","trips":0,"status":0,"url":"rs4oudt0"},{"userId":1092479,"firstName":"marja","lastName":"streppel","pictureGuid":"defaultBSubJUizD","trips":0,"status":0,"url":"ka6yqlkt"},{"userId":1508001,"firstName":"Petra","lastName":"Goossen","pictureGuid":"defaultqHucxbfz9","trips":0,"status":0,"url":"ooprupbk"}],"pictures":[{"createDate":1683973302415,"guid":"TLqZVaBV4fEtM2AQ","height":4032,"width":3024},{"createDate":1683976880062,"guid":"TLqZtX9LqpxapAcJ","height":4032,"width":3024},{"createDate":1683979348671,"guid":"TLqZg2AmoPRRDC6A","height":2736,"width":3648},{"createDate":1683980713656,"guid":"TLqZnypBxsZQWbXn","height":3024,"width":4032},{"createDate":1684003725000,"guid":"TLrcMLVMPUSWPNVT","height":768,"width":1024},{"createDate":1683985126025,"guid":"TLqZZoCyuxwTRyMp","height":4032,"width":3024},{"createDate":1684003857000,"guid":"TLrdVMNmsKyCEGTV","height":1024,"width":768},{"createDate":1684003748000,"guid":"TLrcjmXAlj36Pz4T","height":1024,"width":768},{"createDate":1683984157328,"guid":"TLqZgrtE0K90eUBx","height":4032,"width":3024}],"editors":[{"userId":711078,"firstName":"Manon","lastName":"Goossen","pictureGuid":"defaultJw7wNqgUG","trips":10,"status":0,"url":"6pyqzqbn"}],"fitness":null},{"id":91542594,"tripId":2729842,"categoryId":11,"visibility":1,"comment":"Daar gaan we dan!","lat":32.005532,"lng":34.88541120000001,"deleted":false,"create":1683956880947,"timezone":"Europe/Amsterdam","sync":1685299643051,"authorId":711078,"top1LikeId":3,"top2LikeId":4,"likeCount":4,"userLikeId":0,"commentCount":0,"topReacted":[{"userId":1508755,"firstName":"Tanja","lastName":"Linthorst","pictureGuid":"LOnK2R4ERcoEmC0J","trips":0,"status":0,"url":"rs4oudt0"},{"userId":1550159,"firstName":"Lily","lastName":"Goossen-Turubassa","pictureGuid":"default4F469Uemb","trips":0,"status":0,"url":"ldpfiusc"},{"userId":1527475,"firstName":"Conny","lastName":"Kluin","pictureGuid":"LRsrhLGcd9butNl0","trips":0,"status":0,"url":"24vbu68m"}],"pictures":[{"createDate":1683956880947,"guid":"TLeAepIc4x1Yy77a","height":4032,"width":3024}],"editors":[{"userId":711078,"firstName":"Manon","lastName":"Goossen","pictureGuid":"defaultJw7wNqgUG","trips":10,"status":0,"url":"6pyqzqbn"}],"fitness":null},{"id":91542505,"tripId":2729842,"categoryId":11,"visibility":1,"comment":"Vanochtend zijn we om 02:00 opgestaan om onze vlucht naar vliegveld Ben-Gurion te halen. Eenmaal aangekomen bij het st. Maartenserf bleek opa tegen alle verwachtingen in al klaar te staan. Dat is in die 86 jaar nog nooit eerder voorkomen. Opa heeft er in elk geval zin in!\n\nEenmaal op Schiphol kregen we speciale assistentie, waarbij we o.a. met voorrang mochten inchecken en opa met een soort hoogwerker het vliegtuig in werd getakeld. Uiteraard heeft hij ondertussen alle assistentiemedewerkers uitgebreid over het shantykoor verteld. Bij de security kreeg hij geen voorkeursbehandeling: de stok moest door de X-ray en opa moest gefouilleerd worden.\n\nWe schijnen wind mee te hebben, dus over 4 uurtjes zijn we in Israël!","lat":32.005532,"lng":34.88541120000001,"deleted":false,"create":1683955653001,"timezone":"Europe/Amsterdam","sync":1684165002932,"authorId":711078,"top1LikeId":4,"top2LikeId":9,"likeCount":8,"userLikeId":0,"commentCount":0,"topReacted":[{"userId":1508755,"firstName":"Tanja","lastName":"Linthorst","pictureGuid":"LOnK2R4ERcoEmC0J","trips":0,"status":0,"url":"rs4oudt0"},{"userId":2974378,"firstName":"Jan","lastName":"Turubassa","pictureGuid":"defaultVAL-8b3Jn","trips":0,"status":0,"url":"powy358l"},{"userId":1792805,"firstName":"Edo","lastName":"van Kooten","pictureGuid":"MEM1rwMkwyiVoLko","trips":0,"status":0,"url":"7az5xjsz"}],"pictures":[{"createDate":1683945104994,"guid":"TLeqTuQLtKHbF4Ix","height":4032,"width":3024},{"createDate":1683945278288,"guid":"TLeqMW62xe74vdMW","height":4032,"width":3024},{"createDate":1683955493000,"guid":"TLeqIQTBzMKJdlX0","height":1024,"width":768}],"editors":[{"userId":711078,"firstName":"Manon","lastName":"Goossen","pictureGuid":"defaultJw7wNqgUG","trips":10,"status":0,"url":"6pyqzqbn"}],"fitness":null},{"id":91542572,"tripId":2729842,"categoryId":100,"visibility":1,"comment":"{\"countryCode\":\"IL\"}","lat":0,"lng":0,"deleted":false,"create":1683955652001,"timezone":"Europe/Amsterdam","sync":1684164914346,"authorId":711078,"top1LikeId":0,"top2LikeId":0,"likeCount":0,"userLikeId":0,"commentCount":0,"topReacted":[],"pictures":[{"createDate":1401544404000,"guid":"000000000S0IL000","height":941,"width":1087}],"editors":[{"userId":711078,"firstName":"Manon","lastName":"Goossen","pictureGuid":"defaultJw7wNqgUG","trips":10,"status":0,"url":"6pyqzqbn"}],"fitness":null}]}